ptgnn/__init__.py
ptgnn/__version__.py
ptgnn/py.typed
ptgnn/baseneuralmodel/__init__.py
ptgnn/baseneuralmodel/abstractneuralmodel.py
ptgnn/baseneuralmodel/distributedtrainer.py
ptgnn/baseneuralmodel/modulewithmetrics.py
ptgnn/baseneuralmodel/trainer.py
ptgnn/baseneuralmodel/utils/__init__.py
ptgnn/baseneuralmodel/utils/amlutils.py
ptgnn/baseneuralmodel/utils/data.py
ptgnn/baseneuralmodel/utils/oom.py
ptgnn/implementations/__init__.py
ptgnn/implementations/graph2seq/__init__.py
ptgnn/implementations/graph2seq/graph2seq.py
ptgnn/implementations/graph2seq/test.py
ptgnn/implementations/graph2seq/train.py
ptgnn/implementations/graph2seq/trainandtest.py
ptgnn/implementations/ppi/__init__.py
ptgnn/implementations/ppi/dataloader.py
ptgnn/implementations/ppi/ppi.py
ptgnn/implementations/ppi/train.py
ptgnn/implementations/typilus/__init__.py
ptgnn/implementations/typilus/graph2class.py
ptgnn/implementations/typilus/predict.py
ptgnn/implementations/typilus/train.py
ptgnn/implementations/typilus/traindistributed.py
ptgnn/implementations/varmisuse/__init__.py
ptgnn/implementations/varmisuse/candidateannotatedembeddings.py
ptgnn/implementations/varmisuse/train.py
ptgnn/implementations/varmisuse/varmisuse.py
ptgnn/neuralmodels/__init__.py
ptgnn/neuralmodels/mlp.py
ptgnn/neuralmodels/embeddings/__init__.py
ptgnn/neuralmodels/embeddings/linearmapembedding.py
ptgnn/neuralmodels/embeddings/strelementrepresentationmodel.py
ptgnn/neuralmodels/gnn/__init__.py
ptgnn/neuralmodels/gnn/graphneuralnetwork.py
ptgnn/neuralmodels/gnn/structs.py
ptgnn/neuralmodels/gnn/messagepassing/__init__.py
ptgnn/neuralmodels/gnn/messagepassing/abstractmessagepassing.py
ptgnn/neuralmodels/gnn/messagepassing/egcmessagepassing.py
ptgnn/neuralmodels/gnn/messagepassing/gatedmessagepassing.py
ptgnn/neuralmodels/gnn/messagepassing/globalgraphexchange.py
ptgnn/neuralmodels/gnn/messagepassing/graphnorm.py
ptgnn/neuralmodels/gnn/messagepassing/mlpmessagepassing.py
ptgnn-0.10.4.dist-info/LICENSE
ptgnn-0.10.4.dist-info/METADATA
ptgnn-0.10.4.dist-info/WHEEL
ptgnn-0.10.4.dist-info/top_level.txt
ptgnn-0.10.4.dist-info/RECORD
