Metadata-Version: 2.1
Name: ptgnn
Version: 0.10.4
Summary: Graph Neural Network library for PyTorch
Home-page: https://github.com/microsoft/ptgnn/
Author: Deep Procedural Intelligence
License: MIT
Project-URL: Bug Tracker, https://github.com/microsoft/ptgnn/issues
Project-URL: Documentation, https://github.com/microsoft/ptgnn/tree/master/docs
Project-URL: Source Code, https://github.com/microsoft/ptgnn
Platform: UNKNOWN
Classifier: License :: OSI Approved :: MIT License
Classifier: Topic :: Software Development :: Libraries
Classifier: Typing :: Typed
Classifier: Programming Language :: Python :: 3.6
Classifier: Programming Language :: Python :: 3.7
Classifier: Programming Language :: Python :: 3.8
Requires-Python: >=3.6.1
License-File: LICENSE
Requires-Dist: dpu-utils (>=0.2.17)
Requires-Dist: jellyfish
Requires-Dist: numpy
Requires-Dist: torch-scatter (>=2.0.4)
Requires-Dist: torch (>=1.4.0)
Requires-Dist: tqdm
Requires-Dist: typing-extensions
Provides-Extra: aml
Requires-Dist: azureml ; extra == 'aml'
Provides-Extra: dev
Requires-Dist: black ; extra == 'dev'
Requires-Dist: isort ; extra == 'dev'
Requires-Dist: pre-commit ; extra == 'dev'
